{
  "workPeriod": {
    "name": "근무기간",
    "collection": [
      "1주일이하",
      "1년이상",
      "하루(1일)",
      "1개월~3개월",
      "1주일~1개월",
      "6개월~1년",
      "3개월~6개월"
    ]
  },
  "workDays": {
    "name": "근무요일",
    "collection": [
      "월~일",
      "월~토",
      "월~금",
      "주말(토,일)",
      "주6일",
      "주5일",
      "주4일",
      "주3일",
      "주2일",
      "주1일"
    ]
  },
  "workTime": {
    "name": "근무시간",
    "collection": [
      "오전 파트",
      "오후 파트",
      "저녁 파트",
      "새벽 파트",
      "오전~오후 파트",
      "오후~저녁 파트",
      "저녁~새벽 파트",
      "새벽~오전 파트",
      "풀타임(8시간 이상)"
    ]
  },
  "gender": {
    "name": "성별",
    "collection": ["무관", "남성", "여성"]
  },
  "employmentType": {
    "name": "고용형태",
    "maxCount": 7,
    "type": "selection",
    "collection": [
      "알바",
      "정규직",
      "계약직",
      "파견직",
      "청년인턴",
      "위촉직(프리랜서)",
      "연수생/교육생"
    ]
  }
}
